<mml:dataDictionary xmlns:mml="http://macmillanlearning.com">
  <mml:systemID/>
  <mml:uri/>
  <mml:dataCreated>2015-04-12 10:35</mml:dataCreated>
  <mml:dateLastModified>2015-04-12 11:30</mml:dateLastModified>
  <mml:objectType>DataDictionary</mml:objectType>
  <mml:dictionaryType>file-format</mml:dictionaryType>
  <mml:dictionaryValues>
    <mml:dictionaryValue>ePub</mml:dictionaryValue>
    <mml:dictionaryValue>Digital First</mml:dictionaryValue>
  </mml:dictionaryValues>
</mml:dataDictionary>

